{
  "version": "1.0.0",
  "description": "Screenshot definitions for Operaton documentation",

  "defaults": {
    "viewport": { "width": 1920, "height": 1080 },
    "deviceScaleFactor": 2,
    "waitForSelector": ".content-wrapper",
    "waitTimeout": 10000
  },

  "categories": {
    "cockpit": {
      "description": "Cockpit webapp screenshots",
      "baseUrl": "/operaton/app/cockpit/default"
    },
    "tasklist": {
      "description": "Tasklist webapp screenshots",
      "baseUrl": "/operaton/app/tasklist/default"
    },
    "admin": {
      "description": "Admin webapp screenshots",
      "baseUrl": "/operaton/app/admin/default"
    },
    "welcome": {
      "description": "Welcome webapp screenshots",
      "baseUrl": "/operaton/app/welcome/default"
    }
  },

  "screenshots": [
    {
      "id": "cockpit-dashboard",
      "category": "cockpit",
      "description": "Cockpit main dashboard",
      "path": "#/dashboard",
      "outputFile": "documentation/webapps/cockpit/dashboard.png",
      "waitForSelector": ".dashboard",
      "requirements": {
        "deployments": ["invoice-process", "order-process"],
        "instances": { "invoice-process": 5, "order-process": 3 }
      }
    },
    {
      "id": "cockpit-dashboard-metrics",
      "category": "cockpit",
      "description": "Cockpit metrics view",
      "path": "#/dashboard",
      "outputFile": "documentation/webapps/cockpit/dashboard-metrics.png",
      "selector": ".metrics-section",
      "requirements": {
        "instances": { "any": 10 }
      }
    },
    {
      "id": "cockpit-process-definition-view",
      "category": "cockpit",
      "description": "Process definition view in Cockpit",
      "path": "#/process-definition/{processDefinitionKey}",
      "outputFile": "documentation/webapps/cockpit/bpmn/process-definition-view.png",
      "variables": {
        "processDefinitionKey": "invoice"
      },
      "requirements": {
        "deployments": ["invoice-process"],
        "instances": { "invoice": 3 }
      }
    },
    {
      "id": "cockpit-process-instance-view",
      "category": "cockpit",
      "description": "Process instance detail view",
      "path": "#/process-instance/{processInstanceId}",
      "outputFile": "documentation/webapps/cockpit/bpmn/process-instance-view.png",
      "dynamicVariable": "processInstanceId",
      "requirements": {
        "activeInstance": "invoice"
      }
    },
    {
      "id": "cockpit-failed-jobs",
      "category": "cockpit",
      "description": "Failed jobs view",
      "path": "#/dashboard",
      "outputFile": "documentation/webapps/cockpit/bpmn/cockpit-failed-job-drill-down.png",
      "requirements": {
        "failedJobs": 2
      }
    },
    {
      "id": "cockpit-batch-operations",
      "category": "cockpit",
      "description": "Batch operations page",
      "path": "#/batch",
      "outputFile": "documentation/webapps/cockpit/batch/batch.png",
      "requirements": {
        "batches": 1
      }
    },
    {
      "id": "cockpit-deployments",
      "category": "cockpit",
      "description": "Deployments page",
      "path": "#/repository",
      "outputFile": "documentation/webapps/cockpit/cockpit-deployments-page.png",
      "requirements": {
        "deployments": ["invoice-process", "order-process", "review-invoice"]
      }
    },
    {
      "id": "cockpit-history-view",
      "category": "cockpit",
      "description": "Process definition history view",
      "path": "#/process-definition/{processDefinitionKey}/history",
      "outputFile": "documentation/webapps/cockpit/bpmn/cockpit-history-view-process-definition-history.png",
      "variables": {
        "processDefinitionKey": "invoice"
      },
      "requirements": {
        "completedInstances": { "invoice": 5 }
      }
    },
    {
      "id": "cockpit-heatmap",
      "category": "cockpit",
      "description": "Process heatmap view",
      "path": "#/process-definition/{processDefinitionKey}/history",
      "outputFile": "documentation/webapps/cockpit/bpmn/cockpit-heatmap.png",
      "actions": ["enableHeatmap"],
      "variables": {
        "processDefinitionKey": "invoice"
      }
    },
    {
      "id": "cockpit-dmn-dashboard",
      "category": "cockpit",
      "description": "DMN decisions dashboard",
      "path": "#/decisions",
      "outputFile": "documentation/webapps/cockpit/dmn/cockpit-decision-definition-list.png",
      "requirements": {
        "deployments": ["invoice-decision", "dish-decision"]
      }
    },
    {
      "id": "cockpit-decision-definition-view",
      "category": "cockpit",
      "description": "Decision definition view",
      "path": "#/decision-definition/{decisionDefinitionKey}",
      "outputFile": "documentation/webapps/cockpit/dmn/cockpit-decision-definition-view.png",
      "variables": {
        "decisionDefinitionKey": "invoice-assign-approver"
      }
    },
    {
      "id": "cockpit-decision-instance-view",
      "category": "cockpit",
      "description": "Decision instance detail view",
      "path": "#/decision-instance/{decisionInstanceId}",
      "outputFile": "documentation/webapps/cockpit/dmn/cockpit-decision-instance-view.png",
      "dynamicVariable": "decisionInstanceId",
      "requirements": {
        "decisionInstances": { "invoice-assign-approver": 1 }
      }
    },
    {
      "id": "cockpit-cmmn-dashboard",
      "category": "cockpit",
      "description": "CMMN cases dashboard",
      "path": "#/cases",
      "outputFile": "documentation/webapps/cockpit/cmmn/case-dashboard-deployed.png",
      "requirements": {
        "deployments": ["loan-application-case"]
      }
    },
    {
      "id": "cockpit-case-definition-view",
      "category": "cockpit",
      "description": "Case definition view",
      "path": "#/case-definition/{caseDefinitionKey}",
      "outputFile": "documentation/webapps/cockpit/cmmn/case-definition-view.png",
      "variables": {
        "caseDefinitionKey": "loan_application"
      }
    },
    {
      "id": "cockpit-migration-step1",
      "category": "cockpit",
      "description": "Process instance migration - step 1",
      "path": "#/migration",
      "outputFile": "documentation/webapps/cockpit/bpmn/migration/step1.png",
      "requirements": {
        "multipleVersions": "invoice"
      }
    },
    {
      "id": "cockpit-cleanup-page",
      "category": "cockpit",
      "description": "History cleanup configuration",
      "path": "#/cleanup",
      "outputFile": "documentation/webapps/cockpit/cockpit-cleanup-page.png"
    },
    {
      "id": "cockpit-duration-report",
      "category": "cockpit",
      "description": "Duration report",
      "path": "#/reports/process-instance-duration-report",
      "outputFile": "documentation/webapps/cockpit/duration-report.png",
      "requirements": {
        "completedInstances": { "any": 10 }
      }
    },

    {
      "id": "tasklist-dashboard",
      "category": "tasklist",
      "description": "Tasklist main dashboard",
      "path": "#/",
      "outputFile": "documentation/webapps/tasklist/tasklist-dashboard.png",
      "requirements": {
        "tasks": { "user": "demo", "count": 5 }
      }
    },
    {
      "id": "tasklist-task-detail",
      "category": "tasklist",
      "description": "Task detail view",
      "path": "#/?task={taskId}",
      "outputFile": "documentation/webapps/tasklist/tasklist-task-detail.png",
      "dynamicVariable": "taskId",
      "requirements": {
        "tasks": { "user": "demo", "count": 1 }
      }
    },
    {
      "id": "tasklist-create-filter",
      "category": "tasklist",
      "description": "Create filter dialog",
      "path": "#/",
      "outputFile": "documentation/webapps/tasklist/tasklist-create-filter.png",
      "actions": ["openCreateFilterDialog"]
    },
    {
      "id": "tasklist-filter-detail",
      "category": "tasklist",
      "description": "Filter detail/edit view",
      "path": "#/",
      "outputFile": "documentation/webapps/tasklist/tasklist-filter-detail.png",
      "actions": ["openFilterDetail"]
    },
    {
      "id": "tasklist-generic-form",
      "category": "tasklist",
      "description": "Generic task form",
      "path": "#/?task={taskId}",
      "outputFile": "documentation/webapps/tasklist/tasklist-generic-form.png",
      "dynamicVariable": "taskId"
    },

    {
      "id": "admin-users",
      "category": "admin",
      "description": "User management page",
      "path": "#/users",
      "outputFile": "documentation/webapps/admin/admin-users.png",
      "requirements": {
        "users": ["demo", "john", "mary", "peter"]
      }
    },
    {
      "id": "admin-groups",
      "category": "admin",
      "description": "Group management page",
      "path": "#/groups",
      "outputFile": "documentation/webapps/admin/admin-groups.png",
      "requirements": {
        "groups": ["camunda-admin", "accounting", "management", "sales"]
      }
    },
    {
      "id": "admin-tenants",
      "category": "admin",
      "description": "Tenant management page",
      "path": "#/tenants",
      "outputFile": "documentation/webapps/admin/admin-tenants.png",
      "requirements": {
        "tenants": ["tenant1", "tenant2"]
      }
    },
    {
      "id": "admin-authorizations",
      "category": "admin",
      "description": "Authorization management",
      "path": "#/authorization?resource=0",
      "outputFile": "documentation/webapps/admin/admin-authorization.png"
    },
    {
      "id": "admin-system-settings",
      "category": "admin",
      "description": "System settings page",
      "path": "#/system",
      "outputFile": "documentation/webapps/admin/admin-system-management.png"
    },
    {
      "id": "admin-execution-metrics",
      "category": "admin",
      "description": "Execution metrics page",
      "path": "#/system?section=execution-metrics",
      "outputFile": "documentation/webapps/admin/admin-execution-metrics.png"
    },

    {
      "id": "welcome-dashboard",
      "category": "welcome",
      "description": "Welcome page dashboard",
      "path": "#/welcome",
      "outputFile": "documentation/webapps/welcome/welcome-dashboard-plugin.png"
    },
    {
      "id": "welcome-profile",
      "category": "welcome",
      "description": "User profile page",
      "path": "#/profile",
      "outputFile": "documentation/webapps/welcome/welcome-profile-plugin.png"
    }
  ],

  "processes": {
    "invoice-process": {
      "name": "Invoice Receipt",
      "key": "invoice",
      "file": "processes/bpmn/invoice.bpmn",
      "description": "Standard invoice processing workflow",
      "variables": {
        "amount": 1000,
        "creditor": "Great Pizza for Everyone Inc.",
        "invoiceNumber": "I-12345",
        "invoiceCategory": "Travel Expenses"
      }
    },
    "order-process": {
      "name": "Order Process",
      "key": "order-process",
      "file": "processes/bpmn/order-process.bpmn",
      "description": "Order fulfillment process"
    },
    "review-invoice": {
      "name": "Review Invoice",
      "key": "reviewInvoice",
      "file": "processes/bpmn/review-invoice.bpmn",
      "description": "Invoice review subprocess"
    },
    "loan-application": {
      "name": "Loan Application",
      "key": "loan_application",
      "file": "processes/cmmn/loan-application.cmmn",
      "description": "Loan application case"
    }
  },

  "decisions": {
    "invoice-decision": {
      "name": "Invoice Assignment",
      "key": "invoice-assign-approver",
      "file": "processes/dmn/invoice-assign-approver.dmn",
      "description": "Assigns approver based on amount"
    },
    "dish-decision": {
      "name": "Dish Decision",
      "key": "dish",
      "file": "processes/dmn/dish-decision.dmn",
      "description": "Example dish decision table"
    }
  },

  "users": [
    {
      "id": "demo",
      "firstName": "Demo",
      "lastName": "Demo",
      "email": "demo@operaton.org",
      "password": "demo"
    },
    {
      "id": "john",
      "firstName": "John",
      "lastName": "Doe",
      "email": "john@operaton.org",
      "password": "john"
    },
    {
      "id": "mary",
      "firstName": "Mary",
      "lastName": "Smith",
      "email": "mary@operaton.org",
      "password": "mary"
    },
    {
      "id": "peter",
      "firstName": "Peter",
      "lastName": "Parker",
      "email": "peter@operaton.org",
      "password": "peter"
    }
  ],

  "groups": [
    { "id": "camunda-admin", "name": "Camunda Admin", "type": "SYSTEM" },
    { "id": "accounting", "name": "Accounting", "type": "WORKFLOW" },
    { "id": "management", "name": "Management", "type": "WORKFLOW" },
    { "id": "sales", "name": "Sales", "type": "WORKFLOW" }
  ]
}
